[
	{
        "latlng": {"latitude": 35.64808, "longitude": 139.741614},
        "title": "ラーメン二郎 三田本店",
        "open": "12:00～16:00 18:00～24:00 （夜の臨時休業がある） ランチ営業、夜10時以降入店可、日曜営業",
        "holiday": ["sun", "pub"],
        "urls": {"tabelog": "https://tabelog.com/tokyo/A1314/A131402/13006051/"}
    },
    {
        "latlng": {"latitude": 35.534902, "longitude": 139.705734},
        "title": "ラーメン二郎 京急川崎店",
        "open": "[月～金]     11:00～14:00     18:00～22:00     [土]     11:00～16:00     ランチ営業",    "holiday": ["sat","sun"],
        "holiday": ["sun", "pub"],
        "urls": {"tabelog": "https://tabelog.com/kanagawa/A1405/A140501/14000765/"}
    },
    {
        "latlng": {"latitude": 35.62931 , "longitude": 139.710459},
        "title": "ラーメン二郎 目黒店",
        "open": "8:30～15:00     17:00～20:00     （昼・夜共、材料が無くなり時、早仕舞い）     朝食営業、ランチ営業",
        "holiday": ["wed"],
        "urls": {"tabelog": "https://tabelog.com/tokyo/A1316/A131601/13003449/"}
    }
]
